LICENSE
README.md
setup.cfg
setup.py
usbinfo/__init__.py
usbinfo/__main__.py
usbinfo/darwin.py
usbinfo/linux.py
usbinfo/posix.py
usbinfo.egg-info/PKG-INFO
usbinfo.egg-info/SOURCES.txt
usbinfo.egg-info/dependency_links.txt
usbinfo.egg-info/entry_points.txt
usbinfo.egg-info/top_level.txt